README.md
setup.py
scripts/create_jwks.py
scripts/make_req.py
scripts/packer.py
src/fedoidcmsg/__init__.py
src/fedoidcmsg/bundle.py
src/fedoidcmsg/entity.py
src/fedoidcmsg/file_system.py
src/fedoidcmsg/operator.py
src/fedoidcmsg/signing_service.py
src/fedoidcmsg/site_setup.py
src/fedoidcmsg/test_utils.py
src/fedoidcmsg/utils.py
src/fedoidcmsg.egg-info/PKG-INFO
src/fedoidcmsg.egg-info/SOURCES.txt
src/fedoidcmsg.egg-info/dependency_links.txt
src/fedoidcmsg.egg-info/not-zip-safe
src/fedoidcmsg.egg-info/requires.txt
src/fedoidcmsg.egg-info/top_level.txt